calculator_task/__init__.py
calculator_task/api_helper.py
calculator_task/calculator_task_client.py
calculator_task/configuration.py
calculator_task/decorators.py
calculator_task/controllers/__init__.py
calculator_task/controllers/base_controller.py
calculator_task/controllers/simple_calculator_controller.py
calculator_task/exceptions/__init__.py
calculator_task/exceptions/api_exception.py
calculator_task/http/__init__.py
calculator_task/http/http_call_back.py
calculator_task/http/http_client.py
calculator_task/http/http_context.py
calculator_task/http/http_method_enum.py
calculator_task/http/http_request.py
calculator_task/http/http_response.py
calculator_task/http/requests_client.py
calculator_task/models/__init__.py
calculator_task/models/operation_type_enum.py
Calculator_Task-1.0.dist-info/LICENSE
Calculator_Task-1.0.dist-info/METADATA
Calculator_Task-1.0.dist-info/WHEEL
Calculator_Task-1.0.dist-info/top_level.txt
Calculator_Task-1.0.dist-info/RECORD
